CHANGES.rst
README.rst
development.ini
setup.cfg
setup.py
kotti_contentpreview/__init__.py
kotti_contentpreview/fanstatic.py
kotti_contentpreview/populate.py
kotti_contentpreview/views.py
kotti_contentpreview.egg-info/PKG-INFO
kotti_contentpreview.egg-info/SOURCES.txt
kotti_contentpreview.egg-info/dependency_links.txt
kotti_contentpreview.egg-info/entry_points.txt
kotti_contentpreview.egg-info/not-zip-safe
kotti_contentpreview.egg-info/requires.txt
kotti_contentpreview.egg-info/top_level.txt
kotti_contentpreview/locale/kotti_contentpreview.pot
kotti_contentpreview/locale/de/LC_MESSAGES/kotti_contentpreview.po
kotti_contentpreview/locale/en/LC_MESSAGES/kotti_contentpreview.po
kotti_contentpreview/static/kotti_contentpreview.css
kotti_contentpreview/static/kotti_contentpreview.js
kotti_contentpreview/static/kotti_contentpreview.min.css
kotti_contentpreview/static/kotti_contentpreview.min.js
kotti_contentpreview/tests/conftest.py
kotti_contentpreview/tests/test_configure.py
kotti_contentpreview/tests/test_views.py
local/CHANGES.rst
local/README.rst
local/development.ini
local/setup.cfg
local/setup.py
local/kotti_contentpreview/__init__.py
local/kotti_contentpreview/fanstatic.py
local/kotti_contentpreview/populate.py
local/kotti_contentpreview/views.py
local/kotti_contentpreview/locale/kotti_contentpreview.pot
local/kotti_contentpreview/locale/de/LC_MESSAGES/kotti_contentpreview.po
local/kotti_contentpreview/locale/en/LC_MESSAGES/kotti_contentpreview.po
local/kotti_contentpreview/static/kotti_contentpreview.css
local/kotti_contentpreview/static/kotti_contentpreview.js
local/kotti_contentpreview/static/kotti_contentpreview.min.css
local/kotti_contentpreview/static/kotti_contentpreview.min.js
local/kotti_contentpreview/tests/conftest.py
local/kotti_contentpreview/tests/test_configure.py
local/kotti_contentpreview/tests/test_views.py