Metadata-Version: 1.1
Name: kotti-contentpreview
Version: 0.1a2
Summary: Content preview in Kotti's contents view
Home-page: https://github.com/j23d/kotti_contentpreview
Author: Marco Scheidhuber
Author-email: j23d@jusid.de
License: BSD-derived (http://www.repoze.org/LICENSE.txt)
Keywords: kotti theme
Platform: UNKNOWN
Classifier: Environment :: Web Environment
Classifier: Framework :: Pylons
Classifier: Framework :: Pyramid
Classifier: Intended Audience :: Developers
Classifier: License :: OSI Approved :: BSD License
Classifier: Operating System :: OS Independent
Classifier: Programming Language :: Python
Classifier: Programming Language :: Python :: 2.6
Classifier: Programming Language :: Python :: 2.7
Classifier: Topic :: Internet :: WWW/HTTP
Classifier: Topic :: Software Development :: User Interfaces
